qmcblip/__init__.py
qmcblip/champ.py
qmcblip/champio.py
qmcblip/tools.py
qmcblip/flare/__init__.py
qmcblip/flare/otf.py
qmcblip/flare/quicksim.py
qmcblip/flare/utils.py
qmcblip/flare/verlet.py
qmcblip/gamess/__init__.py
qmcblip/gamess/utils.py
qmcblip/sgdml/__init__.py
qmcblip/sgdml/quicksim.py
qmcblip/sgdml/utils.py
tests/__init__.py
tests/test_champ.py
tests/test_champio.py
tests/gamess/__init__.py
tests/gamess/test_gamess.py
QMCblip-1.0.7.dist-info/LICENSE
QMCblip-1.0.7.dist-info/METADATA
QMCblip-1.0.7.dist-info/WHEEL
QMCblip-1.0.7.dist-info/top_level.txt
QMCblip-1.0.7.dist-info/RECORD
