Metadata-Version: 2.1
Name: QMCblip
Version: 1.0.7
Summary: A small package to couple Quantum Monte Carlo codes to Machine Learning Force Fields through ASE.
Home-page: https://github.com/NLESC-JCER/QMCblip
Author: Emiel Slootman
Author-email: e.slootman@esciencecenter.nl
License: Apache Software License 2.0
Project-URL: Bug Tracker, https://github.com/NLESC-JCER/QMCblip/issues
Classifier: Programming Language :: Python :: 3
Classifier: Topic :: Scientific/Engineering :: Physics
Classifier: Topic :: Scientific/Engineering :: Chemistry
Classifier: License :: OSI Approved :: Apache Software License
Classifier: Operating System :: OS Independent
Requires-Python: >=3.7, <3.10
License-File: LICENSE
Requires-Dist: ase (==3.22.1)
Requires-Dist: mir-flare (==0.2.4)
Requires-Dist: flare-pp (==0.1.1)
Requires-Dist: numpy (==1.20.3)
Requires-Dist: matplotlib (==3.1.2)
Requires-Dist: pydantic (==1.9.0)
Requires-Dist: periodictable (==1.6.0)
Requires-Dist: sgdml (==0.4.10)
